LICENSE
nhelper/__init__.py
nhelper/behavior.py
nhelper/generator.py
nhelper/performers/__init__.py
nhelper/performers/lightning_performer.py
nhelper/performers/performer.py
nhelper/testpack/__init__.py
nhelper/testpack/pt_dataloader.py
nhelper/testpack/testpack.py
nhelper/types.py
nhelper-0.1.0.dist-info/LICENSE
nhelper-0.1.0.dist-info/WHEEL
nhelper-0.1.0.dist-info/METADATA
nhelper-0.1.0.dist-info/RECORD
