Metadata-Version: 2.1
Name: nhelper
Version: 0.1.0
Summary: 🧪 Behavioral tests for NLP models 🧪
Home-page: https://github.com/JulesBelveze/nhelper
License: LICENSE
Keywords: nlp,behavioral testing,test
Author: JulesBelveze
Author-email: jules.belveze@hotmail.fr
Requires-Python: >=3.8,<4.0
Classifier: License :: Other/Proprietary License
Classifier: Programming Language :: Python :: 3
Classifier: Programming Language :: Python :: 3.10
Classifier: Programming Language :: Python :: 3.8
Classifier: Programming Language :: Python :: 3.9
Classifier: Topic :: Scientific/Engineering :: Artificial Intelligence
Classifier: Topic :: Software Development :: Testing
Classifier: Topic :: Text Processing
Requires-Dist: overrides (>=6.1.0,<7.0.0)
Requires-Dist: pydantic (<1.8.0)
Requires-Dist: pytorch-lightning (>=1.6.4,<2.0.0)
Requires-Dist: sentencepiece (>=0.1.96)
Requires-Dist: tabulate (>=0.8.10,<0.9.0)
Requires-Dist: tokenizers (>=0.11.1,<0.12.0)
Requires-Dist: torch (>=1.11.0,<2.0.0)
Requires-Dist: transformers (>=4.18.0,<5.0.0)
Project-URL: Repository, https://github.com/JulesBelveze/nhelper
